{
    "1": {
        "id": 1,
        "nombre": "La Cage Aux Queens",
        "sala":"scenario",
        "nombreSala": "Pablo Neruda",
        "fecha":"02-12-2024",
        "hora":"08:45",
        "teatro": "Paseo La Plaza",
        "valor": 10000

    },
    "2": {
        "id": 2,
        "nombre":"Concert 2 Primaria",
        "sala":"scenario2",
        "nombreSala": "Pablo Neruda",
        "fecha":"28-11-2024",
        "hora":"08:45",
        "teatro": "Paseo La Plaza",
        "valor": 10000

    },
    "3": {
        "id": 3,
        "nombre":"Concert 3 Kinder",
        "sala":"scenario3",
        "nombreSala": "Pablo Neruda",
        "fecha":"29-11-2024",
        "hora":"08:45",
        "teatro": "Paseo La Plaza",
        "valor": 10000
    }
}